{
  "project_info": {
    "project_number": "361022462296",
    "project_id": "otpverifyapp-253de",
    "storage_bucket": "otpverifyapp-253de.appspot.com"
  },
  "client": [
    {
      "client_info": {
        "mobilesdk_app_id": "1:361022462296:android:9cb4291369c1c7b86aed2d",
        "android_client_info": {
          "package_name": "com.example.otpverifications"
        }
      },
      "oauth_client": [
        {
          "client_id": "361022462296-7ghfdupeen65pr6pphl6geqk17vffg45.apps.googleusercontent.com",
          "client_type": 3
        }
      ],
      "api_key": [
        {
          "current_key": "AIzaSyADz2XwK4sih9YhegXZw_IyAv1rQg0vygE"
        }
      ],
      "services": {
        "appinvite_service": {
          "other_platform_oauth_client": [
            {
              "client_id": "361022462296-7ghfdupeen65pr6pphl6geqk17vffg45.apps.googleusercontent.com",
              "client_type": 3
            }
          ]
        }
      }
    }
  ],
  "configuration_version": "1"
}